smat_cli/__init__.py
smat_cli/cli.py
smat_cli/formatters.py
smat_cli/smat.py
smat_cli-0.1.3.dist-info/LICENSE
smat_cli-0.1.3.dist-info/WHEEL
smat_cli-0.1.3.dist-info/entry_points.txt
smat_cli-0.1.3.dist-info/METADATA
smat_cli-0.1.3.dist-info/RECORD
