Metadata-Version: 2.1
Name: smat-cli
Version: 0.1.3
Summary: A command line tool and library to get data from the Social Media Analysis Toolkit (SMAT).
Home-page: https://gitlab.com/dhosterman/smat-cli
License: Public Domain
Author: dhosterman
Author-email: daniel@danielhosterman.com
Requires-Python: >=3.7,<4
Classifier: License :: Other/Proprietary License
Classifier: Programming Language :: Python :: 3
Classifier: Programming Language :: Python :: 3.7
Classifier: Programming Language :: Python :: 3.8
Classifier: Programming Language :: Python :: 3.9
Classifier: Programming Language :: Python :: 3.10
Classifier: Programming Language :: Python :: 3.11
Requires-Dist: click (>=8.0.4,<9.0.0)
Requires-Dist: requests (>=2.27.1,<3.0.0)
Requires-Dist: urllib3 (>=1.26.9,<2.0.0)
Project-URL: Documentation, https://gitlab.com/dhosterman/smat-cli/-/blob/main/README.md
Project-URL: Repository, https://gitlab.com/dhosterman/smat-cli
